ActiveDirectoryService/__init__.py
ActiveDirectoryService/__main__.py
ActiveDirectoryService/api.py
ActiveDirectoryService/api_test.py
ActiveDirectoryService/client.py
ActiveDirectoryService/const.py
ActiveDirectoryService/findBy.py
ActiveDirectoryService/service.py
ActiveDirectoryService/service_api.py
ActiveDirectoryService/userHomeDirectoryACLFix.py
pih_ad-1.22.dist-info/METADATA
pih_ad-1.22.dist-info/WHEEL
pih_ad-1.22.dist-info/entry_points.txt
pih_ad-1.22.dist-info/top_level.txt
pih_ad-1.22.dist-info/RECORD
