Metadata-Version: 2.1
Name: pih-ad
Version: 1.22
Summary: PIH Active directory service package
Home-page: https://pacifichosp.com/
Author: Nikita Karachentsev
Author-email: it@pacifichosp.com
License: MIT
Requires-Dist: ipih
Requires-Dist: pyad
Requires-Dist: pywin32
Requires-Dist: wmi
